<Publication>
  <authors>
    <Author>
      <firstName>Monika</firstName>
      <lastName>Lanzenberger</lastName>
    </Author>
    <Author>
      <firstName>Margit</firstName>
      <lastName>Pohl</lastName>
    </Author>
  </authors>
  <id>TUW-137078</id>
  <title>Usability Study of the ECIC Learning System</title>
  <abstractText>
			The aim of the ECIC project is the dissemination of participative methods of organizational development&lt;br&gt; originating from Scandinavian countries to other European countries. To support this process we&lt;br&gt; developed a hypertextual learning system. Because of the heterogeneous target group and the illstructured&lt;br&gt; domains of ECIC detailed usability testing is necessary. First tentative results indicate that&lt;br&gt; graphical overview maps play an important role and interactive examples are very motivating.
		</abstractText>
  <linkPdf>http://www.ifs.tuwien.ac.at/~mlanzenberger/publications/edmedia2002</linkPdf>
</Publication>