<Publication>
  <id>TUW-200950</id>
  <title>On the Complexity of Some Colorful Problems Parameterized by Treewidth</title>
  <abstractText> This research has been supported by the Australian Research Council through the Australian Centre in Bioinformatics. The first author also acknowledges the support provided by a Fel- lowship to the Institute of Advanced Studies, Durham University, and the support of the Informatics Institute at the University of Bergen during an extended visit.</abstractText>
  <keywords/>
  <authors/>
  <affiliations/>
  <sections>
    <Section>
      <title>1 Introduction</title>
      <type>deo:Introduction</type>
      <typeEnum>INTRODUCTION</typeEnum>
      <referenceIds/>
      <referenceCitations/>
    </Section>
    <Section>
      <title>2 Some Coloring Problems That Are Hard for Treewidth</title>
      <type>DoCO:Section</type>
      <typeEnum>METHOD</typeEnum>
      <referenceIds/>
      <referenceCitations/>
    </Section>
    <Section>
      <title>3 Discussion and Open Problems</title>
      <type>DoCO:Section</type>
      <typeEnum>METHOD</typeEnum>
      <referenceIds/>
      <referenceCitations/>
    </Section>
  </sections>
  <citationContexts/>
  <references>
    <Reference>
      <id>ref71</id>
      <referenceIdString>71</referenceIdString>
      <authors/>
      <referenceText>[Al00] N. Alon. Restricted colorings of graphs. In: Surveys in Combinatorics 1993 (K. Walker, ed.), London Math. Soc. Lecture Notes Series 187 (Cambridge Univ. Press, 1993), 1–33.</referenceText>
      <publication reference="/Publication[1]"/>
    </Reference>
    <Reference>
      <id>ref73</id>
      <referenceIdString>73</referenceIdString>
      <authors/>
      <referenceText>[ALS91] S. Arnborg, J. Lagergren and D. Seese. Easy problems for tree-decomposable graphs. J. Algorithms 12 (1991), 308–340.</referenceText>
      <publication reference="/Publication[1]"/>
    </Reference>
    <Reference>
      <id>ref74</id>
      <referenceIdString>74</referenceIdString>
      <authors/>
      <referenceText>[BF05] H. L. Bodlaender and F. V. Fomin. Equitable colorings of bounded treewidth graphs. Theoretical Computer Science 349 (2005), 22–30.</referenceText>
      <publication reference="/Publication[1]"/>
    </Reference>
    <Reference>
      <id>ref75</id>
      <referenceIdString>75</referenceIdString>
      <authors/>
      <referenceText>[BFLRRW06] H. L. Bodlaender, M. Fellows, M. Langston, M. A. Ragan, F. Rosamond and M. Weyer. Quadratic kernelization for convex recoloring of trees. Proceedings COCOON 2007, Springer-Verlag, Lecture Notes in Computer Science , 2007, to appear.</referenceText>
      <publication reference="/Publication[1]"/>
    </Reference>
    <Reference>
      <id>ref76</id>
      <referenceIdString>76</referenceIdString>
      <authors/>
      <referenceText>[BPT92] R. B. Borie, R. G. Parker and C. A. Tovey. Automatic generation of linear-time algorithms from predicate calculus descriptions of problems on recursively generated graph families. Algorithmica 7 (1992), 555–581.</referenceText>
      <publication reference="/Publication[1]"/>
    </Reference>
    <Reference>
      <id>ref77</id>
      <referenceIdString>77</referenceIdString>
      <authors/>
      <referenceText>[CFRRRS07] B. Chor, M. Fellows, M. A. Ragan, I. Razgon, F. Rosamond and S. Snir. Connected coloring completion for general graphs: algorithms and complexity. Proceedings COCOON 2007, Springer-Verlag, Lecture Notes in Computer Science , 2007, to appear.</referenceText>
      <publication reference="/Publication[1]"/>
    </Reference>
    <Reference>
      <id>ref78</id>
      <referenceIdString>78</referenceIdString>
      <authors/>
      <referenceText>[Cou90] B. Courcelle. The monadic second-order logic of graphs I: Recognizable sets of finite graphs. Information and Computation , 85:12–75, 1990.</referenceText>
      <publication reference="/Publication[1]"/>
    </Reference>
    <Reference>
      <id>ref79</id>
      <referenceIdString>79</referenceIdString>
      <authors/>
      <referenceText>[DF99] R. G. Downey and M. R. Fellows. Parameterized Complexity . Springer-Verlag, 1999.</referenceText>
      <publication reference="/Publication[1]"/>
    </Reference>
    <Reference>
      <id>ref80</id>
      <referenceIdString>80</referenceIdString>
      <authors/>
      <referenceText>[ERT80] P. Erdös, A. L. Rubin and H. Taylor. Choosability in graphs. Congressus Numerantium 26 (1980), 122–157.</referenceText>
      <publication reference="/Publication[1]"/>
    </Reference>
    <Reference>
      <id>ref81</id>
      <referenceIdString>81</referenceIdString>
      <authors/>
      <referenceText>[FG06] J. Flum and M. Grohe, Parameterized Complexity Theory , Springer-Verlag, 2006.</referenceText>
      <publication reference="/Publication[1]"/>
    </Reference>
    <Reference>
      <id>ref82</id>
      <referenceIdString>82</referenceIdString>
      <authors/>
      <referenceText>[FGKPRWY07] M. Fellows, P. Giannopoulos, C. Knauer, C. Paul, F. Rosamond, S. Whitesides and N. Yu. The lawnmower and other problems: applications of MSO logic in geometry. Manuscript, 2007.</referenceText>
      <publication reference="/Publication[1]"/>
    </Reference>
    <Reference>
      <id>ref83</id>
      <referenceIdString>83</referenceIdString>
      <authors/>
      <referenceText>[FHR07] M. Fellows, D. Hermelin and F. Rosamond. On the fixed-parameter intractability and tractability of multiple-interval graph properties. Manuscript, 2007.</referenceText>
      <publication reference="/Publication[1]"/>
    </Reference>
    <Reference>
      <id>ref84</id>
      <referenceIdString>84</referenceIdString>
      <authors/>
      <referenceText>[JS97] K. Jansen and P. Scheffler. Generalized colorings for tree-like graphs. Discrete Applied Mathematics 75 (1997), 135–155.</referenceText>
      <publication reference="/Publication[1]"/>
    </Reference>
    <Reference>
      <id>ref85</id>
      <referenceIdString>85</referenceIdString>
      <authors/>
      <referenceText>[JT95] T. R. Jensen and B. Toft. Graph Coloring Problems . Wiley Interscience, 1995.</referenceText>
      <publication reference="/Publication[1]"/>
    </Reference>
    <Reference>
      <id>ref86</id>
      <referenceIdString>86</referenceIdString>
      <authors/>
      <referenceText>[KPW03] A. V. Kostochka, M. J. Pelsmajer and D. B. West. A list analogue of equitable coloring. Journal of Graph Theory 44 (2003), 166–177.</referenceText>
      <publication reference="/Publication[1]"/>
    </Reference>
    <Reference>
      <id>ref87</id>
      <referenceIdString>87</referenceIdString>
      <authors/>
      <referenceText>[KTV98] J. Kratochvil, Z. Tuza and M. Voigt. New trends in the theory of graph colorings: choosability and list coloring. In: Contemporary Trends in Discrete Mathematics (from DIMACS and DIMATIA to the future) (R. Graham, et al., eds.), DIMACS Series in Discrete Mathematics and Theoretical Computer Science, vol. 49 (AMS, Providence, 1999), 183– 197.</referenceText>
      <publication reference="/Publication[1]"/>
    </Reference>
    <Reference>
      <id>ref88</id>
      <referenceIdString>88</referenceIdString>
      <authors/>
      <referenceText>[Ma04] D. Marx. Graph coloring with local and global constraints. Ph.D. dissertation , Department of Computer Science and Information Theory, Budapest University of Technology and Economics, 2004.</referenceText>
      <publication reference="/Publication[1]"/>
    </Reference>
    <Reference>
      <id>ref89</id>
      <referenceIdString>89</referenceIdString>
      <authors/>
      <referenceText>[Mey73] W. Meyer. Equitable coloring. American Mathematical Monthly 80 (1973), 920–922.</referenceText>
      <publication reference="/Publication[1]"/>
    </Reference>
    <Reference>
      <id>ref90</id>
      <referenceIdString>90</referenceIdString>
      <authors/>
      <referenceText>[Nie06] R. Niedermeier. Invitation to Fixed Parameter Algorithms. Oxford University Press, 2006.</referenceText>
      <publication reference="/Publication[1]"/>
    </Reference>
    <Reference>
      <id>ref91</id>
      <referenceIdString>91</referenceIdString>
      <authors/>
      <referenceText>[Th94] C. Thomassen. Every planar graph is 5-choosable. J. Combinatorial Theory Ser. B 62 (1994), 180–181.</referenceText>
      <publication reference="/Publication[1]"/>
    </Reference>
    <Reference>
      <id>ref92</id>
      <referenceIdString>92</referenceIdString>
      <authors/>
      <referenceText>[Tu97] Z. Tuza. Graph colorings with local constraints — A survey. Discussiones Mathematicae – Graph Theory 17 (1997), 161–228.</referenceText>
      <publication reference="/Publication[1]"/>
    </Reference>
    <Reference>
      <id>ref93</id>
      <referenceIdString>93</referenceIdString>
      <authors/>
      <referenceText>[Viz76] V. G. Vizing. Coloring the vertices of a graph in prescribed colors. Metody Diskret. Anal. v Teorii Kodov i Schem 29 (1976), 3–10. (In Russian.)</referenceText>
      <publication reference="/Publication[1]"/>
    </Reference>
    <Reference>
      <id>ref94</id>
      <referenceIdString>94</referenceIdString>
      <authors/>
      <referenceText>[Wo01] D. R. Woodall. List colourings of graphs, in: Surveys in Combinatorics 2001 (J. W. P. Hirschfeld, ed.) London Math. Soc. Lecture Notes Series 288 (Cambridge Univ. Press, 2001), 269–301.</referenceText>
      <publication reference="/Publication[1]"/>
    </Reference>
  </references>
</Publication>