<Publication>
  <id>TUW-138544</id>
  <title>MODELLING OF VISUAL FEATURE DERIVATION IN THE VIZIR FRAMEWORK</title>
  <keywords/>
  <authors>
    <Author>
      <name>
Horst Eidenberger
</name>
      <firstNames/>
      <affiliations/>
    </Author>
    <Author>
      <name>Horst Eidenberger</name>
      <firstNames/>
      <affiliations/>
    </Author>
  </authors>
  <affiliations/>
  <sections>
    <Section>
      <title>
ABSTRACT
</title>
      <type>abstract</type>
      <typeEnum>ABSTRACT</typeEnum>
      <referenceIds/>
      <referenceCitations/>
    </Section>
    <Section>
      <title>
1. INTRODUCTION
</title>
      <type>keywords</type>
      <typeEnum>KEYWORDS</typeEnum>
      <referenceIds/>
      <referenceCitations/>
    </Section>
    <Section>
      <title>
2. BACKGROUND
</title>
      <type>introduction</type>
      <typeEnum>INTRODUCTION</typeEnum>
      <referenceIds/>
      <referenceCitations/>
    </Section>
    <Section>
      <title>
3. THE VIZIR PROJECT
</title>
      <type>method</type>
      <typeEnum>METHOD</typeEnum>
      <referenceIds/>
      <referenceCitations/>
    </Section>
    <Section>
      <title>
4. FEATURE DERIVATION MODELLING
</title>
      <type>method</type>
      <typeEnum>METHOD</typeEnum>
      <referenceIds/>
      <referenceCitations/>
    </Section>
    <Section>
      <title>
5. CONCLUSION
</title>
      <type>conclusions</type>
      <typeEnum>CONCLUSIONS</typeEnum>
      <referenceIds/>
      <referenceCitations/>
    </Section>
    <Section>
      <title>
ACKNOWLEDGEMENTS
</title>
      <type>acknowledgments</type>
      <typeEnum>ACKNOWLEDGEMENTS</typeEnum>
      <referenceIds/>
      <referenceCitations/>
    </Section>
    <Section>
      <title>
REFERENCES
</title>
      <type>references</type>
      <typeEnum>REFERENCES</typeEnum>
      <referenceIds/>
      <referenceCitations/>
    </Section>
  </sections>
  <citationContexts/>
  <references>
    <Reference>
      <id>ref1</id>
      <marker>[1]</marker>
      <title>Overview of the MPEG-7 standard&quot;,</title>
      <source>IEEE Transactions on Circuits and Systems for Video Technology,</source>
      <authors>
        <ReferenceAuthor>
          <name>S F Chang</name>
          <firstNames/>
        </ReferenceAuthor>
        <ReferenceAuthor>
          <name>T Sikora</name>
          <firstNames/>
        </ReferenceAuthor>
        <ReferenceAuthor>
          <name>A Puri</name>
          <firstNames/>
        </ReferenceAuthor>
      </authors>
      <volume>11</volume>
      <publicationYear>2001</publicationYear>
      <publication reference="/Publication[1]"/>
    </Reference>
    <Reference>
      <id>ref2</id>
      <marker>[2]</marker>
      <title>VizIR – A Framework for Visual Information Retrieval&quot;,</title>
      <authors>
        <ReferenceAuthor>
          <name>H Eidenberger</name>
          <firstNames/>
        </ReferenceAuthor>
        <ReferenceAuthor>
          <name>C Breiteneder</name>
          <firstNames/>
        </ReferenceAuthor>
      </authors>
      <volume>14</volume>
      <publicationYear>2003</publicationYear>
      <publication reference="/Publication[1]"/>
    </Reference>
    <Reference>
      <id>ref3</id>
      <marker>[3]</marker>
      <title>Media Handling for Visual Information Retrieval in VizIR&quot;, in</title>
      <source>Proc. SPIE Visual Communications and Image Processing Conference 2003, SPIE</source>
      <authors>
        <ReferenceAuthor>
          <name>H Eidenberger</name>
          <firstNames/>
        </ReferenceAuthor>
      </authors>
      <volume>5150</volume>
      <publicationYear>2003</publicationYear>
      <publication reference="/Publication[1]"/>
    </Reference>
    <Reference>
      <id>ref4</id>
      <marker>[4]</marker>
      <title>Color and texture descriptors&quot;,</title>
      <source>IEEE Transactions on Circuits and Systems for Video Technology,</source>
      <authors>
        <ReferenceAuthor>
          <name>B S Manjunath</name>
          <firstNames/>
        </ReferenceAuthor>
        <ReferenceAuthor>
          <name>J R Ohm</name>
          <firstNames/>
        </ReferenceAuthor>
        <ReferenceAuthor>
          <name>V V Vasudevan</name>
          <firstNames/>
        </ReferenceAuthor>
        <ReferenceAuthor>
          <name>A Yamada</name>
          <firstNames/>
        </ReferenceAuthor>
      </authors>
      <volume>11</volume>
      <publicationYear>2001</publicationYear>
      <publication reference="/Publication[1]"/>
    </Reference>
  </references>
</Publication>