<Publication>
  <id>TUW-201167</id>
  <title>Using a Solution Archive to Enhance Metaheuristics for the Rooted Delay-Constrained Minimum Spanning Tree Problem</title>
  <publicationType>BEITRAEGE_AUS_TAGUNGSBAENDEN</publicationType>
  <maxSectionLayer>1</maxSectionLayer>
  <authors>
    <Author>
      <firstNames>
        <string>Mario</string>
      </firstNames>
      <lastName>Ruthmair</lastName>
      <affiliations>
        <Affiliation>
          <id>aff0</id>
          <institution>Vienna University of Technology</institution>
          <department>Institute of Computer Graphics and Algorithms</department>
          <country>Austria</country>
          <countryCode>AT</countryCode>
        </Affiliation>
      </affiliations>
    </Author>
    <Author>
      <firstNames>
        <string>Andreas</string>
      </firstNames>
      <lastName>Hubmer</lastName>
      <affiliations>
        <Affiliation reference="/Publication[1]/authors[1]/Author[1]/affiliations[1]/Affiliation[1]"/>
      </affiliations>
    </Author>
    <Author>
      <firstNames>
        <string>Günther</string>
        <string>R</string>
      </firstNames>
      <lastName>Raidl</lastName>
      <affiliations>
        <Affiliation reference="/Publication[1]/authors[1]/Author[1]/affiliations[1]/Affiliation[1]"/>
      </affiliations>
    </Author>
  </authors>
  <affiliations>
    <Affiliation reference="/Publication[1]/authors[1]/Author[1]/affiliations[1]/Affiliation[1]"/>
  </affiliations>
  <sections>
    <Section>
      <level>1</level>
      <layer>1</layer>
      <title>Introduction</title>
      <referenceIds>
        <string>ref1</string>
        <string>ref6</string>
        <string>ref4</string>
        <string>ref5</string>
      </referenceIds>
    </Section>
    <Section>
      <level>2</level>
      <layer>1</layer>
      <title>The Solution Archive</title>
      <referenceIds>
        <string>ref3</string>
        <string>ref2</string>
      </referenceIds>
    </Section>
    <Section>
      <level>3</level>
      <layer>1</layer>
      <title>Integration in Metaheuristics</title>
      <referenceIds/>
    </Section>
  </sections>
  <citationContexts/>
  <references>
    <Reference>
      <id>ref1</id>
      <marker>1.</marker>
      <title>Modeling and Solving the Rooted DistanceConstrained Minimum Spanning Tree Problem</title>
      <source>Computers and Operations Research</source>
      <authors>
        <ReferenceAuthor>
          <firstNames>
            <string>L</string>
          </firstNames>
          <lastName>Gouveia</lastName>
        </ReferenceAuthor>
        <ReferenceAuthor>
          <firstNames>
            <string>A</string>
          </firstNames>
          <lastName>Paias</lastName>
        </ReferenceAuthor>
        <ReferenceAuthor>
          <firstNames>
            <string>D</string>
          </firstNames>
          <lastName>Sharma</lastName>
        </ReferenceAuthor>
      </authors>
      <volume>35</volume>
      <issue>2</issue>
      <pageFrom>600</pageFrom>
      <pageTo>613</pageTo>
      <publicationDateString>2008</publicationDateString>
      <publicationYear>2008</publicationYear>
      <publication reference="/Publication[1]"/>
    </Reference>
    <Reference>
      <id>ref2</id>
      <marker>2.</marker>
      <title>Improving Performances of the Genetic Algorithm by Caching</title>
      <source>Computers and Artificial Intelligence</source>
      <authors>
        <ReferenceAuthor>
          <firstNames>
            <string>J</string>
          </firstNames>
          <lastName>Kratica</lastName>
        </ReferenceAuthor>
      </authors>
      <volume>18</volume>
      <issue>3</issue>
      <pageFrom>271</pageFrom>
      <pageTo>283</pageTo>
      <publicationDateString>1999</publicationDateString>
      <publicationYear>1999</publicationYear>
      <publication reference="/Publication[1]"/>
    </Reference>
    <Reference>
      <id>ref3</id>
      <marker>3.</marker>
      <title>Enhancing Genetic Algorithms by a Trie-Based Complete Solution Archive</title>
      <source>Evolutionary Computation in Combinatorial Optimisation { EvoCOP 2010. LNCS, vol. 6022</source>
      <publisher>Springer</publisher>
      <editors>Cowling, P., Merz, P.</editors>
      <authors>
        <ReferenceAuthor>
          <firstNames>
            <string>G</string>
            <string>R</string>
          </firstNames>
          <lastName>Raidl</lastName>
        </ReferenceAuthor>
        <ReferenceAuthor>
          <firstNames>
            <string>B</string>
          </firstNames>
          <lastName>Hu</lastName>
        </ReferenceAuthor>
      </authors>
      <pageFrom>239</pageFrom>
      <pageTo>251</pageTo>
      <publicationDateString>2010</publicationDateString>
      <publicationYear>2010</publicationYear>
      <publication reference="/Publication[1]"/>
    </Reference>
    <Reference>
      <id>ref4</id>
      <marker>4.</marker>
      <title>A Kruskal-Based Heuristic for the Rooted DelayConstrained Minimum Spanning Tree Problem</title>
      <source>EUROCAST 2009. LNCS, vol. 5717</source>
      <publisher>Springer</publisher>
      <editors>Moreno-Díaz, R., Pichler, F., Quesada-Arencibia, A.</editors>
      <authors>
        <ReferenceAuthor>
          <firstNames>
            <string>M</string>
          </firstNames>
          <lastName>Ruthmair</lastName>
        </ReferenceAuthor>
        <ReferenceAuthor>
          <firstNames>
            <string>G</string>
            <string>R</string>
          </firstNames>
          <lastName>Raidl</lastName>
        </ReferenceAuthor>
      </authors>
      <pageFrom>713</pageFrom>
      <pageTo>720</pageTo>
      <publicationDateString>2009</publicationDateString>
      <publicationYear>2009</publicationYear>
      <publication reference="/Publication[1]"/>
    </Reference>
    <Reference>
      <id>ref5</id>
      <marker>5.</marker>
      <title>Variable Neighborhood Search and Ant Colony Optimization for the Rooted Delay-Constrained Minimum Spanning Tree Problem</title>
      <source>PPSN XI, Part II. LNCS, vol. 6239,</source>
      <publisher>Springer</publisher>
      <editors>et al., R.S.</editors>
      <authors>
        <ReferenceAuthor>
          <firstNames>
            <string>M</string>
          </firstNames>
          <lastName>Ruthmair</lastName>
        </ReferenceAuthor>
        <ReferenceAuthor>
          <firstNames>
            <string>G</string>
            <string>R</string>
          </firstNames>
          <lastName>Raidl</lastName>
        </ReferenceAuthor>
      </authors>
      <pageFrom>391</pageFrom>
      <pageTo>400</pageTo>
      <publicationDateString>2010</publicationDateString>
      <publicationYear>2010</publicationYear>
      <publication reference="/Publication[1]"/>
    </Reference>
    <Reference>
      <id>ref6</id>
      <marker>6.</marker>
      <title>The Delay-Constrained Minimum Spanning Tree Problem</title>
      <source>Proceedings of the 2nd IEEE Symposium on Computers and Communications</source>
      <editors>Blum, C., Roli, A., Sampels, M.</editors>
      <authors>
        <ReferenceAuthor>
          <firstNames>
            <string>H</string>
            <string>F</string>
          </firstNames>
          <lastName>Salama</lastName>
        </ReferenceAuthor>
        <ReferenceAuthor>
          <firstNames>
            <string>D</string>
            <string>S</string>
          </firstNames>
          <lastName>Reeves</lastName>
        </ReferenceAuthor>
        <ReferenceAuthor>
          <firstNames>
            <string>Y</string>
          </firstNames>
          <lastName>Viniotis</lastName>
        </ReferenceAuthor>
      </authors>
      <pageFrom>699</pageFrom>
      <pageTo>703</pageTo>
      <publicationDateString>1997</publicationDateString>
      <publicationYear>1997</publicationYear>
      <publication reference="/Publication[1]"/>
    </Reference>
  </references>
</Publication>